nemoria/__init__.py
nemoria/client.py
nemoria/config.py
nemoria/cryptography.py
nemoria/logger.py
nemoria/protocol.py
nemoria/py.typed
nemoria/server.py
nemoria/store.py
nemoria/utils.py
nemoria-1.1.0.dist-info/METADATA
nemoria-1.1.0.dist-info/WHEEL
nemoria-1.1.0.dist-info/licenses/LICENSE
nemoria-1.1.0.dist-info/RECORD
