Metadata-Version: 2.4
Name: nemoria
Version: 1.1.0
Summary: Async TCP in-memory datastore with secure client-server protocol, supporting real-time multi-client CRUD operations.
Project-URL: Homepage, https://github.com/moh-dehghan/nemoria
Project-URL: Repository, https://github.com/moh-dehghan/nemoria
Project-URL: Issues, https://github.com/moh-dehghan/nemoria/issues
Author-email: Moh-Dehghan <m.dehghan.2003@outlook.com>
License: MIT License
License-File: LICENSE
Keywords: asyncio,client,crud,memory,protocol,server,store,tcp
Classifier: Development Status :: 4 - Beta
Classifier: Framework :: AsyncIO
Classifier: Intended Audience :: Developers
Classifier: License :: OSI Approved :: MIT License
Classifier: Operating System :: OS Independent
Classifier: Programming Language :: Python
Classifier: Programming Language :: Python :: 3
Classifier: Programming Language :: Python :: 3.10
Classifier: Programming Language :: Python :: 3.11
Classifier: Programming Language :: Python :: 3.12
Classifier: Programming Language :: Python :: 3.13
Classifier: Topic :: Internet
Classifier: Topic :: Software Development :: Libraries
Requires-Python: >=3.10
Requires-Dist: cryptography>=41.0.0
Requires-Dist: pyroute>=1.0.0
Requires-Dist: pyyaml>=6.0.0
